MANIFEST.in
README.rst
setup.cfg
setup.py
errormator_client/__init__.py
errormator_client/cli.py
errormator_client/client.py
errormator_client/django_middleware.py
errormator_client/exceptions.py
errormator_client/ext_json.py
errormator_client/logger.py
errormator_client/tests.py
errormator_client/utils.py
errormator_client/wsgi.py
errormator_client.egg-info/PKG-INFO
errormator_client.egg-info/SOURCES.txt
errormator_client.egg-info/dependency_links.txt
errormator_client.egg-info/entry_points.txt
errormator_client.egg-info/requires.txt
errormator_client.egg-info/top_level.txt
errormator_client.egg-info/zip-safe
errormator_client/ext/__init__.py
errormator_client/ext/celery.py
errormator_client/ext/flask.py
errormator_client/ext/general.py
errormator_client/ext/pyramid_tween.py
errormator_client/templates/__init__.py
errormator_client/templates/default_template.ini
errormator_client/timing/__init__.py
errormator_client/timing/timing_chameleon.py
errormator_client/timing/timing_dbapi2.py
errormator_client/timing/timing_django_templates.py
errormator_client/timing/timing_httplib.py
errormator_client/timing/timing_jinja2.py
errormator_client/timing/timing_mako.py
errormator_client/timing/timing_memcache.py
errormator_client/timing/timing_pylibmc.py
errormator_client/timing/timing_pymongo.py
errormator_client/timing/timing_pysolr.py
errormator_client/timing/timing_redispy.py
errormator_client/timing/timing_requests.py
errormator_client/timing/timing_urllib.py
errormator_client/timing/timing_urllib2.py
errormator_client/timing/timing_urllib3.py